pulumi_ui/__init__.py
pulumi_ui/cli.py
pulumi_ui/main.py
pulumi_ui/pulumi_state.py
pulumi_ui/routes.py
pulumi_ui/schemas.py
pulumi_ui/settings.py
pulumi_ui/static/index.html
pulumi_ui/static/logo-slim.png
pulumi_ui/static/logo-square-256.png
pulumi_ui/static/logo.png
pulumi_ui/static/vite.svg
pulumi_ui/static/assets/index-5970027f.js
pulumi_ui/static/assets/index-5fca17f7.css
pulumi_ui/static/assets/index-99bb1942.js
pulumi_ui/static/assets/index-9ac2d527.js
pulumi_ui/static/assets/index-bab0ca40.js
pulumi_ui/static/assets/index-cf9fb700.js
pulumi_ui/static/assets/index-fd76b9ba.js
pulumi_ui/static/static/index.css
pulumi_ui/static/static/index.js
pulumi_ui/static/static/static/index-5fca17f7.css
pulumi_ui/static/static/static/index-8deae1ab.js
pulumi_ui-0.2.1.dist-info/METADATA
pulumi_ui-0.2.1.dist-info/WHEEL
pulumi_ui-0.2.1.dist-info/entry_points.txt
pulumi_ui-0.2.1.dist-info/top_level.txt
pulumi_ui-0.2.1.dist-info/RECORD
