Metadata-Version: 2.1
Name: pulumi-ui
Version: 0.2.1
Summary: UI for visualizing self-hosted Pulumi state.
Author-email: Eric Riddoch <some-email@gmail.com>
License: MIT
Requires-Python: >=3.7
Requires-Dist: fastapi-slim
Requires-Dist: pydantic-settings
Requires-Dist: uvicorn[standard]
Requires-Dist: typer
Requires-Dist: boto3
Requires-Dist: cloudpathlib[azure,gs,s3]
Requires-Dist: loguru
Provides-Extra: dev
Requires-Dist: pulumi-ui[release,static-code-qa,test]; extra == "dev"
Provides-Extra: release
Requires-Dist: build; extra == "release"
Requires-Dist: twine; extra == "release"
Provides-Extra: static-code-qa
Requires-Dist: pre-commit; extra == "static-code-qa"
Requires-Dist: pylint; extra == "static-code-qa"
Requires-Dist: black; extra == "static-code-qa"
Requires-Dist: isort; extra == "static-code-qa"
Requires-Dist: flake8; extra == "static-code-qa"
Requires-Dist: flake8-docstrings; extra == "static-code-qa"
Requires-Dist: Flake8-pyproject; extra == "static-code-qa"
Requires-Dist: radon; extra == "static-code-qa"
Provides-Extra: test
Requires-Dist: pytest; extra == "test"
Requires-Dist: pytest-cov; extra == "test"
